[
  { "id": "ci-01", "memberId": "m-01", "timestamp": "2026-05-30T08:15:00Z", "result": "GRANTED", "stampsAfter": 22 },
  { "id": "ci-02", "memberId": "m-02", "timestamp": "2026-05-30T09:00:00Z", "result": "GRANTED", "stampsAfter": 8 },
  { "id": "ci-03", "memberId": "m-03", "timestamp": "2026-05-30T09:30:00Z", "result": "DENIED",  "stampsAfter": 0 },
  { "id": "ci-04", "memberId": "m-04", "timestamp": "2026-05-29T08:00:00Z", "result": "GRANTED", "stampsAfter": 35 },
  { "id": "ci-05", "memberId": "m-05", "timestamp": "2026-05-29T10:00:00Z", "result": "GRANTED", "stampsAfter": 27 },
  { "id": "ci-06", "memberId": "m-06", "timestamp": "2026-05-29T11:00:00Z", "result": "GRANTED", "stampsAfter": 5 },
  { "id": "ci-07", "memberId": "m-07", "timestamp": "2026-05-28T08:30:00Z", "result": "GRANTED", "stampsAfter": 6 },
  { "id": "ci-08", "memberId": "m-08", "timestamp": "2026-05-28T09:15:00Z", "result": "DENIED",  "stampsAfter": 12 },
  { "id": "ci-09", "memberId": "m-09", "timestamp": "2026-05-28T10:00:00Z", "result": "GRANTED", "stampsAfter": 3 },
  { "id": "ci-10", "memberId": "m-10", "timestamp": "2026-05-27T08:00:00Z", "result": "GRANTED", "stampsAfter": 10 },
  { "id": "ci-11", "memberId": "m-01", "timestamp": "2026-05-27T09:00:00Z", "result": "GRANTED", "stampsAfter": 23 },
  { "id": "ci-12", "memberId": "m-12", "timestamp": "2026-05-27T10:30:00Z", "result": "GRANTED", "stampsAfter": 48 },
  { "id": "ci-13", "memberId": "m-04", "timestamp": "2026-05-26T08:00:00Z", "result": "GRANTED", "stampsAfter": 36 },
  { "id": "ci-14", "memberId": "m-05", "timestamp": "2026-05-26T09:00:00Z", "result": "GRANTED", "stampsAfter": 28 },
  { "id": "ci-15", "memberId": "m-06", "timestamp": "2026-05-25T08:30:00Z", "result": "GRANTED", "stampsAfter": 6 },
  { "id": "ci-16", "memberId": "m-10", "timestamp": "2026-05-25T09:00:00Z", "result": "GRANTED", "stampsAfter": 11 },
  { "id": "ci-17", "memberId": "m-01", "timestamp": "2026-05-24T08:00:00Z", "result": "GRANTED", "stampsAfter": 24 },
  { "id": "ci-18", "memberId": "m-02", "timestamp": "2026-05-24T09:30:00Z", "result": "GRANTED", "stampsAfter": 9 },
  { "id": "ci-19", "memberId": "m-09", "timestamp": "2026-05-23T10:00:00Z", "result": "GRANTED", "stampsAfter": 4 },
  { "id": "ci-20", "memberId": "m-12", "timestamp": "2026-05-23T08:00:00Z", "result": "GRANTED", "stampsAfter": 49 },
  { "id": "ci-21", "memberId": "m-04", "timestamp": "2026-05-22T09:00:00Z", "result": "GRANTED", "stampsAfter": 37 },
  { "id": "ci-22", "memberId": "m-07", "timestamp": "2026-05-21T08:30:00Z", "result": "GRANTED", "stampsAfter": 7 },
  { "id": "ci-23", "memberId": "m-05", "timestamp": "2026-05-20T10:00:00Z", "result": "GRANTED", "stampsAfter": 29 },
  { "id": "ci-24", "memberId": "m-10", "timestamp": "2026-05-19T08:00:00Z", "result": "GRANTED", "stampsAfter": 12 },
  { "id": "ci-25", "memberId": "m-01", "timestamp": "2026-05-18T09:00:00Z", "result": "GRANTED", "stampsAfter": 25 },
  { "id": "ci-26", "memberId": "m-06", "timestamp": "2026-05-17T10:00:00Z", "result": "GRANTED", "stampsAfter": 7 },
  { "id": "ci-27", "memberId": "m-02", "timestamp": "2026-05-15T08:30:00Z", "result": "GRANTED", "stampsAfter": 10 },
  { "id": "ci-28", "memberId": "m-04", "timestamp": "2026-05-12T09:00:00Z", "result": "GRANTED", "stampsAfter": 38 },
  { "id": "ci-29", "memberId": "m-12", "timestamp": "2026-05-10T08:00:00Z", "result": "GRANTED", "stampsAfter": 50 },
  { "id": "ci-30", "memberId": "m-07", "timestamp": "2026-05-05T10:00:00Z", "result": "GRANTED", "stampsAfter": 8 }
]